[
  {
    "url": "https://api.github.com/repos/electron/electron/issues/comments/42962952",
    "html_url": "https://github.com/electron/electron/issues/301#issuecomment-42962952",
    "issue_url": "https://api.github.com/repos/electron/electron/issues/301",
    "id": 42962952,
    "user": {
      "login": "deecoolist",
      "id": 3056757,
      "avatar_url": "https://avatars0.githubusercontent.com/u/3056757?v=3",
      "gravatar_id": "",
      "url": "https://api.github.com/users/deecoolist",
      "html_url": "https://github.com/deecoolist",
      "followers_url": "https://api.github.com/users/deecoolist/followers",
      "following_url": "https://api.github.com/users/deecoolist/following{/other_user}",
      "gists_url": "https://api.github.com/users/deecoolist/gists{/gist_id}",
      "starred_url": "https://api.github.com/users/deecoolist/starred{/owner}{/repo}",
      "subscriptions_url": "https://api.github.com/users/deecoolist/subscriptions",
      "organizations_url": "https://api.github.com/users/deecoolist/orgs",
      "repos_url": "https://api.github.com/users/deecoolist/repos",
      "events_url": "https://api.github.com/users/deecoolist/events{/privacy}",
      "received_events_url": "https://api.github.com/users/deecoolist/received_events",
      "type": "User",
      "site_admin": false
    },
    "created_at": "2014-05-13T14:35:51Z",
    "updated_at": "2014-05-13T23:43:17Z",
    "body": "Just question, how to expose (export module or object) to browser/mainwindow's (module.exports) from main.js without using ipc or remote. working example like node Appjs.\n"
  },
  {
    "url": "https://api.github.com/repos/electron/electron/issues/comments/43057476",
    "html_url": "https://github.com/electron/electron/issues/301#issuecomment-43057476",
    "issue_url": "https://api.github.com/repos/electron/electron/issues/301",
    "id": 43057476,
    "user": {
      "login": "zcbenz",
      "id": 639601,
      "avatar_url": "https://avatars3.githubusercontent.com/u/639601?v=3",
      "gravatar_id": "",
      "url": "https://api.github.com/users/zcbenz",
      "html_url": "https://github.com/zcbenz",
      "followers_url": "https://api.github.com/users/zcbenz/followers",
      "following_url": "https://api.github.com/users/zcbenz/following{/other_user}",
      "gists_url": "https://api.github.com/users/zcbenz/gists{/gist_id}",
      "starred_url": "https://api.github.com/users/zcbenz/starred{/owner}{/repo}",
      "subscriptions_url": "https://api.github.com/users/zcbenz/subscriptions",
      "organizations_url": "https://api.github.com/users/zcbenz/orgs",
      "repos_url": "https://api.github.com/users/zcbenz/repos",
      "events_url": "https://api.github.com/users/zcbenz/events{/privacy}",
      "received_events_url": "https://api.github.com/users/zcbenz/received_events",
      "type": "User",
      "site_admin": true
    },
    "created_at": "2014-05-14T08:59:08Z",
    "updated_at": "2014-05-14T08:59:08Z",
    "body": "> Just question, how to expose (export module or object) to browser/mainwindow's (module.exports) from main.js without using ipc or remote. working example like node Appjs.\n\natom-shell uses the multi-processes architecture of Chromium, so there is no way to share JS objects without sending IPC messages.\n"
  },
  {
    "url": "https://api.github.com/repos/electron/electron/issues/comments/43162414",
    "html_url": "https://github.com/electron/electron/issues/301#issuecomment-43162414",
    "issue_url": "https://api.github.com/repos/electron/electron/issues/301",
    "id": 43162414,
    "user": {
      "login": "deecoolist",
      "id": 3056757,
      "avatar_url": "https://avatars0.githubusercontent.com/u/3056757?v=3",
      "gravatar_id": "",
      "url": "https://api.github.com/users/deecoolist",
      "html_url": "https://github.com/deecoolist",
      "followers_url": "https://api.github.com/users/deecoolist/followers",
      "following_url": "https://api.github.com/users/deecoolist/following{/other_user}",
      "gists_url": "https://api.github.com/users/deecoolist/gists{/gist_id}",
      "starred_url": "https://api.github.com/users/deecoolist/starred{/owner}{/repo}",
      "subscriptions_url": "https://api.github.com/users/deecoolist/subscriptions",
      "organizations_url": "https://api.github.com/users/deecoolist/orgs",
      "repos_url": "https://api.github.com/users/deecoolist/repos",
      "events_url": "https://api.github.com/users/deecoolist/events{/privacy}",
      "received_events_url": "https://api.github.com/users/deecoolist/received_events",
      "type": "User",
      "site_admin": false
    },
    "created_at": "2014-05-15T02:22:27Z",
    "updated_at": "2014-05-15T02:32:21Z",
    "body": "Thank you, I did using ipc to communicate. By the way it awesome :-)\nSo, i have clone the latest souce?  \n"
  }
]