[
  {
    "url": "https://api.github.com/repos/electron/electron/issues/comments/254139832",
    "html_url": "https://github.com/electron/electron/issues/7647#issuecomment-254139832",
    "issue_url": "https://api.github.com/repos/electron/electron/issues/7647",
    "id": 254139832,
    "user": {
      "login": "MarshallOfSound",
      "id": 6634592,
      "avatar_url": "https://avatars0.githubusercontent.com/u/6634592?v=3",
      "gravatar_id": "",
      "url": "https://api.github.com/users/MarshallOfSound",
      "html_url": "https://github.com/MarshallOfSound",
      "followers_url": "https://api.github.com/users/MarshallOfSound/followers",
      "following_url": "https://api.github.com/users/MarshallOfSound/following{/other_user}",
      "gists_url": "https://api.github.com/users/MarshallOfSound/gists{/gist_id}",
      "starred_url": "https://api.github.com/users/MarshallOfSound/starred{/owner}{/repo}",
      "subscriptions_url": "https://api.github.com/users/MarshallOfSound/subscriptions",
      "organizations_url": "https://api.github.com/users/MarshallOfSound/orgs",
      "repos_url": "https://api.github.com/users/MarshallOfSound/repos",
      "events_url": "https://api.github.com/users/MarshallOfSound/events{/privacy}",
      "received_events_url": "https://api.github.com/users/MarshallOfSound/received_events",
      "type": "User",
      "site_admin": false
    },
    "created_at": "2016-10-17T08:06:49Z",
    "updated_at": "2016-10-17T08:06:49Z",
    "body": "I don't see how this is an issue with Electron.  It appears to be an issue with a completely different NPM package failing to install on your system.\n\nA cursory google search indicates that install `libjpeg-dev` will solve your issue.\n\n``` bash\nsudo apt-get install libjpeg-dev\n```\n\nIn the future, please keep the Electron issue section only for Electron specific issues 👍 \n"
  }
]