[
  {
    "url": "https://api.github.com/repos/electron/electron/issues/comments/256804402",
    "html_url": "https://github.com/electron/electron/issues/7780#issuecomment-256804402",
    "issue_url": "https://api.github.com/repos/electron/electron/issues/7780",
    "id": 256804402,
    "user": {
      "login": "kevinsawicki",
      "id": 671378,
      "avatar_url": "https://avatars0.githubusercontent.com/u/671378?v=3",
      "gravatar_id": "",
      "url": "https://api.github.com/users/kevinsawicki",
      "html_url": "https://github.com/kevinsawicki",
      "followers_url": "https://api.github.com/users/kevinsawicki/followers",
      "following_url": "https://api.github.com/users/kevinsawicki/following{/other_user}",
      "gists_url": "https://api.github.com/users/kevinsawicki/gists{/gist_id}",
      "starred_url": "https://api.github.com/users/kevinsawicki/starred{/owner}{/repo}",
      "subscriptions_url": "https://api.github.com/users/kevinsawicki/subscriptions",
      "organizations_url": "https://api.github.com/users/kevinsawicki/orgs",
      "repos_url": "https://api.github.com/users/kevinsawicki/repos",
      "events_url": "https://api.github.com/users/kevinsawicki/events{/privacy}",
      "received_events_url": "https://api.github.com/users/kevinsawicki/received_events",
      "type": "User",
      "site_admin": true
    },
    "created_at": "2016-10-28T00:10:30Z",
    "updated_at": "2016-10-28T00:10:30Z",
    "body": "/cc @tarruda is this expected in sandbox mode?\n"
  },
  {
    "url": "https://api.github.com/repos/electron/electron/issues/comments/257792995",
    "html_url": "https://github.com/electron/electron/issues/7780#issuecomment-257792995",
    "issue_url": "https://api.github.com/repos/electron/electron/issues/7780",
    "id": 257792995,
    "user": {
      "login": "tarruda",
      "id": 842846,
      "avatar_url": "https://avatars0.githubusercontent.com/u/842846?v=3",
      "gravatar_id": "",
      "url": "https://api.github.com/users/tarruda",
      "html_url": "https://github.com/tarruda",
      "followers_url": "https://api.github.com/users/tarruda/followers",
      "following_url": "https://api.github.com/users/tarruda/following{/other_user}",
      "gists_url": "https://api.github.com/users/tarruda/gists{/gist_id}",
      "starred_url": "https://api.github.com/users/tarruda/starred{/owner}{/repo}",
      "subscriptions_url": "https://api.github.com/users/tarruda/subscriptions",
      "organizations_url": "https://api.github.com/users/tarruda/orgs",
      "repos_url": "https://api.github.com/users/tarruda/repos",
      "events_url": "https://api.github.com/users/tarruda/events{/privacy}",
      "received_events_url": "https://api.github.com/users/tarruda/received_events",
      "type": "User",
      "site_admin": false
    },
    "created_at": "2016-11-02T07:38:05Z",
    "updated_at": "2016-11-02T07:38:05Z",
    "body": "In this case the opener is null because a window created with `new BrowserWindow` is a top-level window created by the main process. `window.opener` should only be set in a child window that you create with `window.open`. \n"
  },
  {
    "url": "https://api.github.com/repos/electron/electron/issues/comments/260791767",
    "html_url": "https://github.com/electron/electron/issues/7780#issuecomment-260791767",
    "issue_url": "https://api.github.com/repos/electron/electron/issues/7780",
    "id": 260791767,
    "user": {
      "login": "kevinsawicki",
      "id": 671378,
      "avatar_url": "https://avatars0.githubusercontent.com/u/671378?v=3",
      "gravatar_id": "",
      "url": "https://api.github.com/users/kevinsawicki",
      "html_url": "https://github.com/kevinsawicki",
      "followers_url": "https://api.github.com/users/kevinsawicki/followers",
      "following_url": "https://api.github.com/users/kevinsawicki/following{/other_user}",
      "gists_url": "https://api.github.com/users/kevinsawicki/gists{/gist_id}",
      "starred_url": "https://api.github.com/users/kevinsawicki/starred{/owner}{/repo}",
      "subscriptions_url": "https://api.github.com/users/kevinsawicki/subscriptions",
      "organizations_url": "https://api.github.com/users/kevinsawicki/orgs",
      "repos_url": "https://api.github.com/users/kevinsawicki/repos",
      "events_url": "https://api.github.com/users/kevinsawicki/events{/privacy}",
      "received_events_url": "https://api.github.com/users/kevinsawicki/received_events",
      "type": "User",
      "site_admin": true
    },
    "created_at": "2016-11-15T22:32:50Z",
    "updated_at": "2016-11-15T22:32:50Z",
    "body": "Closing this out since it is expected that windows created via `new BrowserWindow` won't have `window.opener` set, only windows created via `window.open` will.\n"
  }
]